workerconnector/__init__.py
workerconnector/app_config.py
workerconnector/capp.py
workerconnector-0.1.0.dist-info/WHEEL
workerconnector-0.1.0.dist-info/METADATA
workerconnector-0.1.0.dist-info/RECORD
